compairer/__init__.py
compairer/core.py
compairer/explanations.py
compairer/methods/__init__.py
compairer/methods/customs.py
compairer/methods/strings.py
compairer/methods/vectors.py
compairer/models/__init__.py
compairer/models/base.py
compairer/models/incremental.py
compairer/utils/__init__.py
compairer/utils/stats.py
compairer-0.1.3.dist-info/LICENSE
compairer-0.1.3.dist-info/METADATA
compairer-0.1.3.dist-info/WHEEL
compairer-0.1.3.dist-info/top_level.txt
compairer-0.1.3.dist-info/RECORD
