Metadata-Version: 2.1
Name: compairer
Version: 0.1.3
Summary: A versatile comparison library for Python
Home-page: https://github.com/schizoprada/compairer
Author: Joel Yisrael
Author-email: joel@sss.bot
Classifier: Programming Language :: Python :: 3
Classifier: License :: OSI Approved :: MIT License
Classifier: Operating System :: OS Independent
Requires-Python: >=3.6
License-File: LICENSE
Requires-Dist: numpy
Requires-Dist: fuzzywuzzy
